{
    "users": [
        {"handle": "vitalikbuterin", "id": 295218901},
        {"handle": "tayvano_", "id": 19748227},
        {"handle": "0xMaki", "id": 1269408213876846592},
        {"handle": "monetsupply", "id": 1226309266715234305},
        {"handle": "danrobinson", "id": 273288231},
        {"handle": "NeerajKA", "id": 14710235},
        {"handle": "DegenSpartan", "id": 1978953986},
        {"handle": "QwQiao", "id": 712457848874086400},
        {"handle": "RyanSAdams", "id": 14571055},
        {"handle": "StaniKulechov", "id": 952921795316912133},
        {"handle": "rleshner", "id": 394480074},
        {"handle": "fintechfrank", "id": 2933805082},
        {"handle": "CryptoHayes", "id": 983993370048630785},
        {"handle": "kaiynne", "id": 24809221},
        {"handle": "jchervinsky", "id": 47003920},
        {"handle": "zhusu", "id": 79714172},
        {"handle": "samczsun", "id": 2844400678},
        {"handle": "santiagoroel", "id": 737132550},
        {"handle": "chaserchapman", "id": 1231590550429675520},
        {"handle": "shegenerates", "id": 1371165914629087235},
        {"handle": "peter_szilagyi", "id": 186028018},
        {"handle": "n2ckchong", "id": 1287487599691456512},
        {"handle": "0xtuba", "id": 1240385359055335429},
        {"handle": "Mudit__Gupta", "id": 122360573},
        {"handle": "reshmasaujani", "id": 57172253},
        {"handle": "lemiscate", "id": 2190759643},
        {"handle": "hudsonjameson", "id": 801236832},
        {"handle": "timbeiko", "id": 80722677},
        {"handle": "gakonst", "id": 804029200315334656},
        {"handle": "matthuang", "id": 44322763},
        {"handle": "transmissions11", "id": 1303125102196711424},
        {"handle": "evabeylin", "id": 342470910},
        {"handle": "_anishagnihotri", "id": 1078014622525988864},
        {"handle": "fomosaurus", "id": 929827324563947521},
        {"handle": "nicksdjohnson", "id": 34592834},
        {"handle": "drakefjustin", "id": 258480276},
        {"handle": "CamiRusso", "id": 421271885},
        {"handle": "protolambda", "id": 735426681968660481},
        {"handle": "DeFi_Dad", "id": 991745162274467840},
        {"handle": "sassal0x", "id": 313724502},
        {"handle": "Arthur_0x", "id": 1357451976},
        {"handle": "RAC", "id": 7976822},
        {"handle": "hosseeb", "id": 231208649},
        {"handle": "mariashen", "id": 27134030},
        {"handle": "kylesamani", "id": 46332443},
        {"handle": "spencernoon", "id": 1527806202},
        {"handle": "iandaos", "id": 2437938810},
        {"handle": "sergeynazarov", "id": 46238620},
        {"handle": "hasufl", "id": 566534886},
        {"handle": "ethereumJoseph", "id": 2362854624}
    ]
}